rws_knmi_lib/__init__.py
rws_knmi_lib/knmi_downloader.py
rws_knmi_lib-1.0.1.dist-info/LICENSE
rws_knmi_lib-1.0.1.dist-info/METADATA
rws_knmi_lib-1.0.1.dist-info/WHEEL
rws_knmi_lib-1.0.1.dist-info/top_level.txt
rws_knmi_lib-1.0.1.dist-info/RECORD
