Metadata-Version: 2.1
Name: rws-knmi-lib
Version: 1.0.1
Summary: Library voor communicatie met KNMI weer data.
Author-email: RWS Datalab <datalab.codebase@rws.nl>
Project-URL: homepage, https://gitlab.com/rwsdatalab/public/codebase/tools/rws-knmi-lib
Project-URL: repository, https://gitlab.com/rwsdatalab/public/codebase/tools/rws-knmi-lib
Project-URL: changelog, https://gitlab.com/rwsdatalab/public/codebase/tools/rws-knmi-lib/blob/main/CHANGELOG.rst
Keywords: rws-knmi-lib
Classifier: Development Status :: 5 - Production/Stable
Classifier: Intended Audience :: Developers
Classifier: Natural Language :: English
Classifier: Programming Language :: Python :: 3
Classifier: Programming Language :: Python :: 3.6
Classifier: Programming Language :: Python :: 3.7
Classifier: Programming Language :: Python :: 3.8
Classifier: Programming Language :: Python :: 3.9
Classifier: Programming Language :: Python :: 3.10
Classifier: License :: OSI Approved :: Apache Software License
Classifier: Operating System :: OS Independent
Requires-Python: >=3.6
License-File: LICENSE
Requires-Dist: mpu
Requires-Dist: pandas
Requires-Dist: requests
Requires-Dist: types-requests
Provides-Extra: dev
Requires-Dist: bandit ; extra == 'dev'
Requires-Dist: black ; extra == 'dev'
Requires-Dist: flake8 ; extra == 'dev'
Requires-Dist: flake8-bugbear ; extra == 'dev'
Requires-Dist: flake8-comprehensions ; extra == 'dev'
Requires-Dist: flake8-docstrings ; extra == 'dev'
Requires-Dist: flake8-polyfill ; extra == 'dev'
Requires-Dist: isort ; extra == 'dev'
Requires-Dist: mypy ; extra == 'dev'
Requires-Dist: pre-commit ; extra == 'dev'
Requires-Dist: pylint ; extra == 'dev'
Requires-Dist: pytest ; extra == 'dev'
Requires-Dist: pytest-cov ; extra == 'dev'
Requires-Dist: radon ; extra == 'dev'
Requires-Dist: rstcheck[sphinx] ; extra == 'dev'
Requires-Dist: safety ; extra == 'dev'
Requires-Dist: sh ; extra == 'dev'
Provides-Extra: doc
Requires-Dist: pydata-sphinx-theme ; extra == 'doc'
Requires-Dist: sphinx ; extra == 'doc'
Requires-Dist: sphinx-autodoc-typehints ; extra == 'doc'
